iconify/__init__.py
iconify/anim.py
iconify/browser.py
iconify/core.py
iconify/fetch.py
iconify/path.py
iconify/qt.py
iconify-0.0.103.data/data/requirements/requirements.txt
iconify-0.0.103.dist-info/LICENSE
iconify-0.0.103.dist-info/METADATA
iconify-0.0.103.dist-info/WHEEL
iconify-0.0.103.dist-info/entry_points.txt
iconify-0.0.103.dist-info/top_level.txt
iconify-0.0.103.dist-info/RECORD
