Metadata-Version: 2.1
Name: iconify
Version: 0.0.103
Summary: An icon and image library for Qt that lets you use svg's from common packs like FontAwesome, MateriallDesign etc.
Home-page: https://github.com/jasongilholme/iconify
Author: Jason Gilholme
Author-email: jasongilholme@gmail.com
License: GPLv3
Keywords: Qt,icons,svg,PySide,PyQt
Platform: OS-independent
Classifier: Development Status :: 3 - Alpha
Classifier: Environment :: X11 Applications :: Qt
Classifier: Intended Audience :: Developers
Classifier: License :: OSI Approved :: GNU General Public License v3 (GPLv3)
Classifier: Operating System :: OS Independent
Classifier: Programming Language :: Python :: 2
Classifier: Programming Language :: Python :: 3
Classifier: Topic :: Software Development :: User Interfaces
